{
    "results": [
      {
        "team": "Maccabi Haifa",
        "manager": "Messay Dego",
        "city": "Haifa",
        "formation": "4-3-3",
        "striker": "Pierrot",
        "lw": "Haziza",
        "rw": "Atzili",
        "cam": "Chery",
        "cm": "Abu-Fani",
        "cdm": "Dia Saba",
        "lb": "Cornud",
        "cb1": "Sean Goldberg",
        "cd2": "Seck",
        "rb": "Sundgren",
        "gk": "Josh Cohen",
        "stadium": "Sammi Ofer Stadium",
        "ticketPrice1": 550,
        "ticketPrice2": 300,
        "ticketPrice3": 100,
        "seats": 30858,
        "fav": false,
        "discription": "Maccabi Haifa is one of the Big Four clubs in Israeli football who has won sixteen league titles six State Cups and five Toto Cups and holds the record for the most Champions League group stage qualifications for an Israeli team in three occasions",
        "logoPic":"src/pictures/Maccabi_Haifa-logo.png",
        "backroundPic": "src/pictures/Maccabi-Haifa.jpg",
        "subscriptionPrice1": 5700,
        "subscriptionPrice2": 2700,
        "subscriptionPrice3": 2000,
        "maincolor":"green"
      },
      {
        "team": "Maccabi Tel Aviv",
        "manager": "Aitor Karanka",
        "city": "Tel Aviv",
        "formation": "4-4-2",
        "striker": "Eran Zahavi",
        "lw": "Ganikovski",
        "rw": "Jovanovic",
        "cam": "Dor Peretz",
        "cm": "Guiagon",
        "cdm": "Glazer",
        "lb": "Davidzada",
        "cb1": "Yeini",
        "cd2": "Nir bitton",
        "rb": "Kandil",
        "gk": "Daniel Peretz",
        "stadium": "Bloomfield stadium",
        "ticketPrice1": 500,
        "ticketPrice2": 280,
        "ticketPrice3": 90,
        "seats": 29500,
        "fav": false,
        "discription": "Maccabi Tel Aviv is one of the top 3 clubs in Israel Founded in 1906 in Jaffa , it is the oldest and most decorated football club in Israel. Maccabi Tel Aviv is the only football team that have never been relegated from the Israeli Premier League and one of only three Israeli teams to ever progress to the UEFA Champions League group stage",
        "logoPic": "src/pictures/Maccabi_Tel_Aviv_logo.png",
        "backroundPic": "src/pictures/Maccabi-Tel-Aviv.jpg",
        "subscriptionPrice1": 4500,
        "subscriptionPrice2": 2600,
        "subscriptionPrice3": 1700,
        "maincolor": "yellow"
      },
      {
        "team": "Hapoel Beer Sheva",
        "manager": "Elyaniv Barda",
        "city": "Beer Sheva",
        "formation": "4-3-3",
        "striker": "Tomer Hemed",
        "lw": "Ramzi Safuri",
        "rw": "Sagiv Yehezkel",
        "cam": "Dor Micha",
        "cm": "Roy Gordana",
        "cdm": "Shai Elias",
        "lb": "Lopes",
        "cb1": "Miguel Vitoe",
        "cd2": "Abu Abaid",
        "rb": "Dayda Or",
        "gk": "Omri Glazer",
        "stadium": "Toto Turner Stadium",
        "ticketPrice1": 500,
        "ticketPrice2": 300,
        "ticketPrice3": 105,
        "seats": 16000,
        "fav": false,
        "discription": "Hapoel Beer Sheva is an Israeli football club from the city of Be'er Sheva, that competes in the Israeli Premier League. The club was established in 1949, and since 2007 it has been run by businesswoman Alona Barkat, who serves as the club's owner.Beer Sheva is the first team in the history of Israeli football to play in a European competition, and the first team in the history of Israeli football that played in the UEFA Cup",
        "logoPic": "src/pictures/hapoel-beer-sheva-logo.png",
        "backroundPic": "src/pictures/hapoel-beer-sheva.jpeg",
        "subscriptionPrice1": 4300,
        "subscriptionPrice2": 2600,
        "subscriptionPrice3": 2000,
        "maincolor": "red"
      },
  
      {
        "team": "Maccabi Netanya",
        "manager": "Ran Kuzuk",
        "city": "Netanya",
        "formation": "4-3-3",
        "striker": "Zlatanovic",
        "lw": "Twumasi",
        "rw": "Oz Bilo",
        "cam": "Eitan Azoulay",
        "cm": "Boris Enow",
        "cdm": "Omri Gendelman",
        "lb": "Ouammmou",
        "cb1": "Raz Shlomo",
        "cd2": "Galabov",
        "rb": "Ido Vaier",
        "gk": "Itamar Nitzan",
        "stadium": "Netanya Stadium",
        "ticketPrice1": 300,
        "ticketPrice2": 200,
        "ticketPrice3": 80,
        "seats": 13800,
        "fav": false,
        "discription": "Netanya is an Israeli football club based in Netanya. Established in 1934, the club was a founding member of the Israeli League in 1949. After winning their first championship in 1971, the club's golden period lasted until the late 80s, including four more league titles and a double in 1978. The club is currently ranked 4th in the Israel Premier League",
        "logoPic": "src/pictures/maccabi-netanya-logo.png",
        "backroundPic": "src/pictures/maccabi-netanya.jpg",
        "subscriptionPrice1": 3300,
        "subscriptionPrice2": 2100,
        "subscriptionPrice3": 1550,
        "maincolor": "yellow"
      },
      {
        "team": "Hapoel Jerusalem",
        "manager": "Ziv Arie",
        "city": "Jerusalem",
        "formation": "4-3-3",
        "striker":"Nadav Aviv Niddam",
        "cdm": "Awka Ashta",
        "lb": "Roy Revivo",
        "cb1": "Baco",
        "cd2": "Amit Glazer",
        "rb": "Eloge Yao",
        "gk": "Adebayo Adeleye",
        "stadium": "Teddi Stadium",
        "ticketPrice1": 290,
        "ticketPrice2": 110,
        "ticketPrice3": 75,
        "seats": 32000,
        "fav": false,
        "discription": "Hapoel Katamon Jerusalem F.C. was the name of the club that is currently called Hapoel Jerusalem. At its founding, Hapoel Katamon Jerusalem became the first fan-owned football club in Israel. In May 2020, the club's Council decided to rename the club's name to Hapoel Jerusalem, and changed the logo accordingly. Hapoel Jerusalem are ranked 5th in the Israeli premier league",
        "logoPic": "src/pictures/hapoel-katamon-jerusalem-logo.png",
        "backroundPic": "src/pictures/hapoel-katamon-jerusalem.jpg",
        "subscriptionPrice1": 3100,
        "subscriptionPrice2": 2050,
        "subscriptionPrice3": 1400,
        "maincolor": "red"
      },
      {
        "team": "M.S Ashdod",
        "manager": "Ran Ben Simon",
        "city": "Ashdod",
        "formation": "4-3-3",
        "striker": "Zakaria Mugeese",
        "lw": "Zakaria Mugeese",
        "rw": "Roy levy",
        "cam": "Shalev Harush",
        "cm": "Naor Sabag",
        "cdm": "Jordan Sebban",
        "lb": "Kamaheni",
        "cb1": "Gil Cohen",
        "cd2": "Cvetkovic",
        "rb": "Tom Ben Zaken",
        "gk": "Yoav Gerafi",
        "stadium": "Yud-Alef",
        "ticketPrice1": 250,
        "ticketPrice2": 120,
        "ticketPrice3": 70,
        "seats": 8000,
        "fav": false,
        "discription": "M.S Ashdod is an Israeli professional football club, playing in the port city of Ashdod. The unusual name of the team (unlike most Israeli football teams, this one only indicates the club's home city without any specific Jewish sporting association, such as Hapoel, Maccabi, or Beitar) is the result of the union of two city rivals, Hapoel Ashdod and Maccabi Ironi Ashdod in 1999. The club currently plays in the Israeli Premier League and is ranked 6th",
        "logoPic": "src/pictures/fc-ashdod-logo.gif",
        "backroundPic": "src/pictures/ashdod.jpg",
        "subscriptionPrice1": 2600,
        "subscriptionPrice2": 1800,
        "subscriptionPrice3": 1400,
        "maincolor": "red"
      },
      {
        "team": "Beitar Jerusalem",
        "manager": "Yossi Abukasis",
        "city": "Jerusalem",
        "formation": "4-3-3",
        "striker": "Nicolaescu",
        "lw": "Yarden Shua",
        "rw": "Danilo Asprilla",
        "cam": "Ofir Kriaf",
        "cm": "Orel Dgani",
        "cdm": "Trazie Thomas",
        "lb": "Grigory Morozov",
        "cb1": "Ori Dahan",
        "cd2": "Orel Dgani",
        "rb": "Avishai Cohen",
        "gk": "Miguel Silva",
        "stadium": "Teddi Stadium",
        "ticketPrice1": 230,
        "ticketPrice2": 140,
        "ticketPrice3": 85,
        "seats": 32000,
        "fav": false,
        "discription": "Beitar Jerusalem is an Israeli football club based in the city of Jerusalem, that plays in the Israeli Premier League. The club has traditionally worn kit colours of yellow and black. The team has played its home matches in Teddy Stadium, the stadium with the largest number of seats in Israel with a capacity of 31,733.The club is one of the most popular in Israel and is among the Israeli clubs with the highest number of fans in the country. The club was founded in 1936 by Shmuel Kirschstein and David Horn and is currently ranked 7th in Israel",
        "logoPic": "src/pictures/Beitar_Jerusalem-logo.png",
        "backroundPic": "src/pictures/Beitar_Jerusalem.jpg",
        "subscriptionPrice1": "3100",
        "subscriptionPrice2": "2600",
        "subscriptionPrice3": "1990",
        "maincolor":"yellow"
      },
  
      {
        "team": "Hapoel Haifa",
        "manager": "Ronny Levi",
        "city": "Haifa",
        "formation": "4-3-3",
        "striker": "Mohammaed Kamara",
        "lw": "Itay Buganim",
        "rw": "Eliel Peretz",
        "cam": "Liran Sardal",
        "cm": "Aleksander Scekic",
        "cdm": "Dor Malul",
        "lb": "Dudi Twito",
        "cb1": "Hatem Elhamed",
        "cd2": "Costas Soteriou",
        "rb": "Guy Mizrahi",
        "gk": "Ohad Levita",
        "stadium": "Sammy Ofer",
        "ticketPrice1": 220,
        "ticketPrice2": 120,
        "ticketPrice3": 70,
        "seats": 30870,
        "fav": false,
        "discription": "Hapoel Haifa is an Israeli football club located in the city of Haifa. The club won one championship (1999) and 4 Israeli cups (1963, 1966, 1974, 2018). The team is also known as The Sharks. The club's home is the Sammy Ofer Stadium in Haifa and the team is currently ranked 8th in Israel",
        "logoPic": "src/pictures/Hapoel-Haifa-logo.png",
        "backroundPic": "src/pictures/Hapoel-Haifa.jpg",
        "subscriptionPrice1": 2700,
        "subscriptionPrice2": 1800,
        "subscriptionPrice3": 1300,
        "maincolor": "blue"
      },
      {
        "team": "Bnei Sakhnin",
        "manager": "Kobi Refua",
        "city": "Sakhnin",
        "formation": "5-3-2",
        "striker": "Ange-Freddy Plumian",
        "lw": "Dor Hugi",
        "rw": "Roei Shukrani",
        "cam": "Guy Melamed",
        "cm": "Beram Kayal",
        "cdm": "Ante Puljic",
        "lb": "Abou Dosso",
        "cb1": "Marwan Kabha",
        "cd2": "Marwan Gantos",
        "rb": "Ovadia Dervish",
        "gk": "Gad Amos",
        "stadium": "Doha Stadium",
        "ticketPrice1": 200,
        "ticketPrice2": 120,
        "ticketPrice3": 85,
        "seats": 8500,
        "fav": false,
        "discription": "Bnei Sakhnin is an Israeli football club based at the Doha Stadium in Sakhnin. They are the most successful club among the Arab-Israeli clubs in the country, having won the State Cup in 2004. Founded in 1991 and wearing red and white, The team is currently ranked 9th in Israel",
        "logoPic": "src/pictures/bnei-sakhnin-logo.png",
        "backroundPic": "src/pictures/sakhnin.jpg",
        "subscriptionPrice1": 2800,
        "subscriptionPrice2": 1990,
        "subscriptionPrice3": 1700,
        "maincolor": "red"
      },
      {
        "team": "Hapoel Hadera",
        "manager": "Menahem Koretzki",
        "city": "Hadera",
        "formation": "5-3-2",
        "striker": "Stav Nachmani",
        "lw": "Samy Bourard",
        "rw": "Ness Zamir",
        "cam": "Roslan Barsky",
        "cm": "Menashe Zalka",
        "cdm": "Saar Fadida",
        "lb": "Klemen Sturn",
        "cb1": "Ido Levy",
        "cd2": "Philip Ipole",
        "rb": "Dia Lababidi",
        "gk": "Robi Levkovich",
        "stadium": "Netanya Stadium",
        "ticketPrice1": 180,
        "ticketPrice2": 90,
        "ticketPrice3": 65,
        "seats": 13800,
        "fav": false,
        "discription": "Hapoel Hadera is an Israeli football club from Hadera. They currently play in the Israeli Premier League, and have previously spent eight seasons in the top division. Founded in 1936 and wearing red and white, Hapoel hadera are ranked 10th in Israel",
        "logoPic": "src/pictures/hapoel-hadera-logo.png",
        "backroundPic": "src/pictures/hapoel-hadera.jpg",
        "subscriptionPrice1": 2600,
        "subscriptionPrice2": 2200,
        "subscriptionPrice3": 1400,
        "maincolor": "red"
      },
      {
        "team": "Hapoel Tel-Aviv",
        "manager": "Haim Silvas",
        "city": "Tel-Aviv",
        "formation": "3-4-2-1",
        "striker": "Qays Ganem",
        "lw": "Alen Ozbolt",
        "rw": "Hrvoje Ilic",
        "cam": "Dan Einbinder",
        "cm": "Godfried Roemeratoe",
        "cdm": "David Keltjens",
        "lb": "Yahav Gurfinkel",
        "cb1": "Stav Lemkin",
        "cd2": "Or Israelov",
        "rb": "Ben Bitton",
        "gk": "Emilijus Zubas",
        "stadium": "Bloomfield stadium",
        "ticketPrice1": 220,
        "ticketPrice2": 130,
        "ticketPrice3": 95,
        "seats": 29500,
        "fav": false,
        "discription": "Hapoel Tel-Aviv is an Israeli football club based in Tel Aviv that competes in the Israeli Premier League. The club's traditional home ground is Bloomfield Stadium. To date, the club has won 13 championships and 16 State Cups. In 1967, Hapoel Tel Aviv became the first club to win the Asian Champion Club Tournament. Since 1995, the club has competed in European club competitions, and has the highest rank among all Israeli clubs, with some outstanding achievements, such as wins against Chelsea, Milan, Hamburg, Paris Saint-Germain, Benfica, Rangers, and Celtic. It is also one of only three Israeli teams to have qualified for the UEFA Champions League group stage, and one of the two that are ordinary members of the European Club Association. Founded in 1923 and wearing red and white, the club is currently ranked 11th in Israel",
        "logoPic": "src/pictures/hapoel-tel-aviv-logo.png",
        "backroundPic": "src/pictures/hapoel-tel-aviv.jpg",
        "subscriptionPrice1": 3300,
        "subscriptionPrice2": 2600,
        "subscriptionPrice3": 1525,
        "maincolor": "red"
      },
      {
        "team": "Bney Reine",
        "manager": "Sharon Mimer",
        "city": "Nazareth",
        "formation": "4-3-3",
        "striker": "Mark Koszta",
        "lw": "Shlomi Azulay",
        "rw": "Gustavo Marmentini",
        "cam": "Amit Meir",
        "cm": "Anicet Abel",
        "cdm": "Richard Boateng",
        "lb": "Abdallah Jaber",
        "cb1": "Lukas Spendlhofer",
        "cd2": "Nir Bardea",
        "rb": "Eyad Khoteiba",
        "gk": "Arik Yanko",
        "stadium": "Green Stadium",
        "ticketPrice1": 220,
        "ticketPrice2": 100,
        "ticketPrice3": 69,
        "seats": 5000,
        "fav": false,
        "discription": "Bnei Reine is an Israeli football club based in Reineh. The club played its home matches at the Municipal Stadium. They were promoted to play with Bnei Sakhnin in the Israeli Premier League as its second Arab-Israeli football club for the 2023 season. In the 1990s and 2000s, Maccabi Bnei Reineh played in Liga Gimel and didn't achieve significant achievements. In 2008 the club was folded. In 2016, the club refounded by a local businessman named Saeed Basul, and at the end of the 2017 season, the team finished in first place in Liga Gimel Jezreel, and promoted to Liga Bet. On 6 May 2022 the club promoted to the Israeli Premier League at the first time in the history of the team. Wearing red and blue, the team is currently ranked 12th in Israel",
        "logoPic": "src/pictures/maccabi-bnei-reine-logo.png",
        "backroundPic": "src/pictures/bney-reine.png",
        "subscriptionPrice1": 2900,
        "subscriptionPrice2": 1990,
        "subscriptionPrice3": 1050,
        "maincolor": "blue"
      },
      {
        "team": "Kiryat Shmona",
        "manager": "Slobodan Drapich",
        "city": "Kiryat Shmona",
        "formation": "4-3-3",
        "striker": "Itamar Shviro",
        "lw": "Senin Sebai",
        "rw": "Muhamad Shaker",
        "cam": "Samuel Broun",
        "cm": "Timothy Muzie",
        "cdm": "Yoav Hofmeister",
        "lb": "Ziv Morgan",
        "cb1": "Itay Ben Shabat",
        "cd2": "Ayad Habashi",
        "rb": "Noam Cohen",
        "gk": "Dziugas Bartkus",
        "stadium": "Kiryat Shmona Municipal Stadium",
        "ticketPrice1": 160,
        "ticketPrice2": 110,
        "ticketPrice3": 60,
        "seats": 5300,
        "fav": false,
        "discription": "Kiryat Shmona is an Israeli football club based in Kiryat Shmona. The club is a current member of the Israeli Premier League, and plays at the Ironi Stadium. The club won their first league title in 2012. The club was founded in 2000 by a merger of Hapoel Kiryat Shmona of Liga Alef and Maccabi Kiryat Shmona of Liga Bet, and took Hapoel Kiryat Shmona's place in Liga Alef, as well as playing at Hapoel's stadium. The club is currently ranked 13th in Israel",
        "logoPic": "src/pictures/ironi-kiryat-shmona-logo.jpg",
        "backroundPic": "src/pictures/ironi-kiryat-shmona.jpg",
        "subscriptionPrice1": 2300,
        "subscriptionPrice2": 1500,
        "subscriptionPrice3": 1100,
        "maincolor": "blue"
      },
      {
        "team": "Sektzia Ness Ziona",
        "manager": "Shlomi Dora",
        "city": "Ness Ziona",
        "formation": "4-3-3",
        "striker": "Mor Fadida",
        "lw": "Yoni Stoyanov",
        "rw": "Almog Buzaglo",
        "cam": "Dor Kochav",
        "cm": "Christian Battocchio",
        "cdm": "Ilay Trost",
        "lb": "Or Rahih",
        "cb1": "Stav Israeli",
        "cd2": "Michael Siroshtein",
        "rb": "Or Roizman",
        "gk": "Yossi Ginzburg",
        "stadium": "Ness Ziona Stadium",
        "ticketPrice1": 130,
        "ticketPrice2": 80,
        "ticketPrice3": 50,
        "seats": 3300,
        "fav": false,
        "discription": "Sekzia Ness Ziona is a football club from the Israeli city of Ness Ziona. Currently play in the Israeli Premier League, the top tier of Israeli football. Home matches were previously played at the Ness Ziona Stadium. Upon their promotion to the Israeli Premier League for the 2020 and 2023 seasons, the club moved its home matches to the HaMoshava Stadium in Petah Tikva. The club was founded as F.S. Nes Ziona in 1955, following a merger of the local football clubs in Ness Ziona. The club is currently ranked 14th and last in the Israeli premier league",
        "logoPic": "src/pictures/sekzia-ness-ziona-logo.gif",
        "backroundPic": "src/pictures/ness-ziona.jpg",
        "subscriptionPrice1": 2000,
        "subscriptionPrice2": 1300,
        "subscriptionPrice3": 990,
        "maincolor": "orange"
     }
    ]
  }
